[
    {
        "id": "ed51dc5f919d2b6c",
        "type": "tab",
        "label": "Flow 1",
        "disabled": false,
        "info": ""
    },
    {
        "id": "945eab85077935a1",
        "type": "function",
        "z": "ed51dc5f919d2b6c",
        "name": "Translating function",
        "func": "if (typeof msg.payload === \"string\") {\n    try {\n        msg.payload = JSON.parse(msg.payload);\n    } catch (e) {\n        node.error(\"Errore nel parsing JSON: \" + e.message);\n        return null;\n    }\n}\n\nif (!msg.payload || !msg.payload.text || !msg.payload.sentiment || !msg.payload.language) {\n    node.warn(\"Dati mancanti nel payload dopo conversione: \" + JSON.stringify(msg.payload));\n    return null;\n}\n\nmsg.payload = [\n    {\n        measurement: \"sentiment_data\",\n        fields: { \n            text: msg.payload.text,\n            sentiment: msg.payload.sentiment,\n            language: msg.payload.language\n        }\n    }\n];\n\nreturn msg;",
        "outputs": 1,
        "timeout": 0,
        "noerr": 0,
        "initialize": "",
        "finalize": "",
        "libs": [],
        "x": 550,
        "y": 300,
        "wires": [
            [
                "e3dbcee07e636ca7",
                "6a5ce124ed98b007"
            ]
        ]
    },
    {
        "id": "61897d30825e2ec4",
        "type": "json",
        "z": "ed51dc5f919d2b6c",
        "name": "",
        "property": "payload",
        "action": "",
        "pretty": true,
        "x": 370,
        "y": 300,
        "wires": [
            [
                "945eab85077935a1",
                "4dd3b53654ed98a5"
            ]
        ]
    },
    {
        "id": "4dd3b53654ed98a5",
        "type": "debug",
        "z": "ed51dc5f919d2b6c",
        "name": "JSON Output",
        "active": true,
        "tosidebar": true,
        "console": false,
        "tostatus": false,
        "complete": "payload",
        "targetType": "msg",
        "statusVal": "",
        "statusType": "auto",
        "x": 510,
        "y": 400,
        "wires": []
    },
    {
        "id": "e3dbcee07e636ca7",
        "type": "debug",
        "z": "ed51dc5f919d2b6c",
        "name": "Database input",
        "active": true,
        "tosidebar": true,
        "console": false,
        "tostatus": false,
        "complete": "payload",
        "targetType": "msg",
        "statusVal": "",
        "statusType": "auto",
        "x": 680,
        "y": 360,
        "wires": []
    },
    {
        "id": "9a4c024355ddb316",
        "type": "debug",
        "z": "ed51dc5f919d2b6c",
        "name": "Data coming from Java app",
        "active": true,
        "tosidebar": true,
        "console": false,
        "tostatus": false,
        "complete": "payload",
        "targetType": "msg",
        "statusVal": "",
        "statusType": "auto",
        "x": 540,
        "y": 120,
        "wires": []
    },
    {
        "id": "6a5ce124ed98b007",
        "type": "influxdb batch",
        "z": "ed51dc5f919d2b6c",
        "influxdb": "0809e3e5344ee420",
        "precision": "",
        "retentionPolicy": "",
        "name": "influxDb",
        "database": "database",
        "precisionV18FluxV20": "s",
        "retentionPolicyV18Flux": "",
        "org": "Sentiment-Analysis-Project",
        "bucket": "sentimentBucket",
        "x": 720,
        "y": 220,
        "wires": []
    },
    {
        "id": "dfe115b552ba65d4",
        "type": "mqtt in",
        "z": "ed51dc5f919d2b6c",
        "name": "PythonSentiment",
        "topic": "python_sentiment_analysis",
        "qos": "0",
        "datatype": "auto-detect",
        "broker": "6f0f4423fa4d637c",
        "nl": false,
        "rap": true,
        "rh": 0,
        "inputs": 0,
        "x": 180,
        "y": 300,
        "wires": [
            [
                "61897d30825e2ec4",
                "54db164d3d930a0a"
            ]
        ]
    },
    {
        "id": "54db164d3d930a0a",
        "type": "debug",
        "z": "ed51dc5f919d2b6c",
        "name": "Data coming from Python app",
        "active": true,
        "tosidebar": true,
        "console": false,
        "tostatus": false,
        "complete": "payload",
        "targetType": "msg",
        "statusVal": "",
        "statusType": "auto",
        "x": 310,
        "y": 460,
        "wires": []
    },
    {
        "id": "e826b7d34f826679",
        "type": "mqtt in",
        "z": "ed51dc5f919d2b6c",
        "name": "JavaSentiment",
        "topic": "java_sentiment_analysis",
        "qos": "0",
        "datatype": "auto-detect",
        "broker": "521ff1aef539c28c",
        "nl": false,
        "rap": true,
        "rh": 0,
        "inputs": 0,
        "x": 200,
        "y": 200,
        "wires": [
            [
                "9a4c024355ddb316",
                "61897d30825e2ec4"
            ]
        ]
    },
    {
        "id": "0809e3e5344ee420",
        "type": "influxdb",
        "hostname": "127.0.0.1",
        "port": 8086,
        "protocol": "http",
        "database": "database",
        "name": "influxDB",
        "usetls": false,
        "tls": "",
        "influxdbVersion": "2.0",
        "url": "http://influxdb:8086",
        "timeout": 10,
        "rejectUnauthorized": true
    },
    {
        "id": "6f0f4423fa4d637c",
        "type": "mqtt-broker",
        "name": "PythonSentiment",
        "broker": "http://mqtt5",
        "port": 1883,
        "clientid": "",
        "autoConnect": true,
        "usetls": false,
        "protocolVersion": 4,
        "keepalive": 60,
        "cleansession": true,
        "autoUnsubscribe": true,
        "birthTopic": "",
        "birthQos": "0",
        "birthRetain": "false",
        "birthPayload": "",
        "birthMsg": {},
        "closeTopic": "",
        "closeQos": "0",
        "closeRetain": "false",
        "closePayload": "",
        "closeMsg": {},
        "willTopic": "",
        "willQos": "0",
        "willRetain": "false",
        "willPayload": "",
        "willMsg": {},
        "userProps": "",
        "sessionExpiry": ""
    },
    {
        "id": "521ff1aef539c28c",
        "type": "mqtt-broker",
        "name": "JavaSentiment",
        "broker": "mqtt5",
        "port": 1883,
        "clientid": "",
        "autoConnect": true,
        "usetls": false,
        "protocolVersion": 4,
        "keepalive": 60,
        "cleansession": true,
        "autoUnsubscribe": true,
        "birthTopic": "",
        "birthQos": "0",
        "birthRetain": "false",
        "birthPayload": "",
        "birthMsg": {},
        "closeTopic": "",
        "closeQos": "0",
        "closeRetain": "false",
        "closePayload": "",
        "closeMsg": {},
        "willTopic": "",
        "willQos": "0",
        "willRetain": "false",
        "willPayload": "",
        "willMsg": {},
        "userProps": "",
        "sessionExpiry": ""
    }
]